.editorconfig
.gitignore
INSTALL.md
MANIFEST.in
README.md
TODO.md
requirements.txt
scrapy.cfg
setup.cfg
setup.py
afaq_dl.egg-info/PKG-INFO
afaq_dl.egg-info/SOURCES.txt
afaq_dl.egg-info/dependency_links.txt
afaq_dl.egg-info/requires.txt
afaq_dl.egg-info/top_level.txt
afaqdl/__init__.py
afaqdl/_version.py
afaqdl/conf.py
afaqdl/config_local.py
afaqdl/items.py
afaqdl/middlewares.py
afaqdl/pipelines.py
afaqdl/settings.py
afaqdl/spiders/__init__.py
afaqdl/spiders/afaq.py
afaqdl/utils/__init__.py
afaqdl/utils/convert.py
afaqdl/utils/git_utils.py
afaqdl/utils/html_util.py
afaqdl/utils/system.py
bin/anarchism_update
man/afaq-dl.8