Metadata-Version: 1.1
Name: afaq-dl
Version: 1.0
Summary: Download the online book An Anarchist FAQ
Home-page: https://github.com/juxor/afaq-dl
Author: juxor
Author-email: ju@riseup.net
License: GPLv3+
Keywords: python scrapy afaq anarchism git html markdown
Platform: UNKNOWN
Classifier: Development Status :: 3 - Alpha
Classifier: Environment :: Console
Classifier: Intended Audience :: End Users/Desktop
Classifier: Intended Audience :: Developers
Classifier: License :: OSI Approved :: GNU General Public License v3 or later (GPLv3+)
Classifier: Operating System :: OS Independent
Classifier: Programming Language :: Python
Classifier: Topic :: Software Development :: Libraries :: Python Modules
